{
  "run_id": "2026-07-14T06:00:01",
  "started_at": "2026-07-14T06:00:01.667650",
  "finished_at": null,
  "status": "running",
  "failed_at": null,
  "steps": [
    {
      "account": "Masterlist",
      "script": "masterlist_fetch.py",
      "exit_code": 0,
      "status": "pass",
      "timestamp": "2026-07-14T06:00:11.384269",
      "error": null
    },
    {
      "account": "Coaching",
      "script": "asana_pull.py",
      "exit_code": 0,
      "status": "pass",
      "timestamp": "2026-07-14T06:00:20.293229",
      "error": null
    },
    {
      "account": "M7",
      "script": "m7_pull.py",
      "exit_code": 0,
      "status": "pass",
      "timestamp": "2026-07-14T06:00:28.397544",
      "error": null
    },
    {
      "account": "DMG",
      "script": "dmg_pull.py",
      "exit_code": 0,
      "status": "pass",
      "timestamp": "2026-07-14T06:00:36.646550",
      "error": null
    },
    {
      "account": "R4H",
      "script": "r4h_pull.py",
      "exit_code": 0,
      "status": "pass",
      "timestamp": "2026-07-14T06:00:45.173331",
      "error": null
    },
    {
      "account": "Parentis Health",
      "script": "parentis_pull.py",
      "exit_code": 0,
      "status": "pass",
      "timestamp": "2026-07-14T06:00:53.251802",
      "error": null
    },
    {
      "account": "Britelift",
      "script": "britelift_pull.py",
      "exit_code": 0,
      "status": "pass",
      "timestamp": "2026-07-14T06:01:01.806030",
      "error": null
    },
    {
      "account": "Britelift Chat",
      "script": "britelift_pull.py",
      "exit_code": 0,
      "status": "pass",
      "timestamp": "2026-07-14T06:01:10.828972",
      "error": null
    }
  ]
}