{
  "run_id": "2026-07-04T06:00:02",
  "started_at": "2026-07-04T06:00:02.411133",
  "finished_at": null,
  "status": "running",
  "failed_at": null,
  "steps": [
    {
      "account": "Masterlist",
      "script": "masterlist_fetch.py",
      "exit_code": 0,
      "status": "pass",
      "timestamp": "2026-07-04T06:00:17.479039",
      "error": null
    },
    {
      "account": "Coaching",
      "script": "asana_pull.py",
      "exit_code": 0,
      "status": "pass",
      "timestamp": "2026-07-04T06:00:31.861083",
      "error": null
    },
    {
      "account": "M7",
      "script": "m7_pull.py",
      "exit_code": 0,
      "status": "pass",
      "timestamp": "2026-07-04T06:00:43.019188",
      "error": null
    },
    {
      "account": "Parentis Health",
      "script": "parentis_pull.py",
      "exit_code": 0,
      "status": "pass",
      "timestamp": "2026-07-04T06:00:54.463690",
      "error": null
    },
    {
      "account": "Britelift",
      "script": "britelift_pull.py",
      "exit_code": 0,
      "status": "pass",
      "timestamp": "2026-07-04T06:01:06.160446",
      "error": null
    },
    {
      "account": "Britelift Chat",
      "script": "britelift_pull.py",
      "exit_code": 0,
      "status": "pass",
      "timestamp": "2026-07-04T06:01:17.771788",
      "error": null
    },
    {
      "account": "RideX",
      "script": "Ridex_pull.py",
      "exit_code": 0,
      "status": "pass",
      "timestamp": "2026-07-04T06:01:29.657032",
      "error": null
    }
  ]
}