{
  "run_id": "2026-07-07T03:00:02",
  "started_at": "2026-07-07T03:00:02.901726",
  "finished_at": null,
  "status": "running",
  "failed_at": null,
  "steps": [
    {
      "account": "Masterlist",
      "script": "masterlist_fetch.py",
      "exit_code": 0,
      "status": "pass",
      "timestamp": "2026-07-07T03:00:16.592983",
      "error": null
    },
    {
      "account": "Coaching",
      "script": "asana_pull.py",
      "exit_code": 0,
      "status": "pass",
      "timestamp": "2026-07-07T03:00:30.666380",
      "error": null
    },
    {
      "account": "M7",
      "script": "m7_pull.py",
      "exit_code": 0,
      "status": "pass",
      "timestamp": "2026-07-07T03:00:43.984918",
      "error": null
    },
    {
      "account": "Parentis Health",
      "script": "parentis_pull.py",
      "exit_code": 0,
      "status": "pass",
      "timestamp": "2026-07-07T03:00:53.815252",
      "error": null
    },
    {
      "account": "Britelift",
      "script": "britelift_pull.py",
      "exit_code": 0,
      "status": "pass",
      "timestamp": "2026-07-07T03:01:04.239510",
      "error": null
    },
    {
      "account": "Britelift Chat",
      "script": "britelift_pull.py",
      "exit_code": 0,
      "status": "pass",
      "timestamp": "2026-07-07T03:01:14.208855",
      "error": null
    },
    {
      "account": "RideX",
      "script": "Ridex_pull.py",
      "exit_code": 0,
      "status": "pass",
      "timestamp": "2026-07-07T03:01:24.029249",
      "error": null
    },
    {
      "account": "Hamilton",
      "script": "Hamilton_pull.py",
      "exit_code": 0,
      "status": "pass",
      "timestamp": "2026-07-07T03:01:50.497948",
      "error": null
    },
    {
      "account": "Skyline",
      "script": "Skyline_pull.py",
      "exit_code": 0,
      "status": "pass",
      "timestamp": "2026-07-07T03:03:07.093572",
      "error": null
    },
    {
      "account": "VIP",
      "script": "vip_pull.py",
      "exit_code": 0,
      "status": "pass",
      "timestamp": "2026-07-07T03:03:31.086276",
      "error": null
    },
    {
      "account": "C&H",
      "script": "ch_pull.py",
      "exit_code": 0,
      "status": "pass",
      "timestamp": "2026-07-07T03:03:41.539137",
      "error": null
    },
    {
      "account": "Reno Cab",
      "script": "rc_pull.py",
      "exit_code": 0,
      "status": "pass",
      "timestamp": "2026-07-07T03:04:01.680063",
      "error": null
    },
    {
      "account": "Trans Iowa",
      "script": "ti_pull.py",
      "exit_code": 0,
      "status": "pass",
      "timestamp": "2026-07-07T03:04:12.552899",
      "error": null
    },
    {
      "account": "Data Carz",
      "script": "dc_pull.py",
      "exit_code": 0,
      "status": "pass",
      "timestamp": "2026-07-07T03:04:34.863035",
      "error": null
    },
    {
      "account": "Associated Cab",
      "script": "ac_pull.py",
      "exit_code": 0,
      "status": "pass",
      "timestamp": "2026-07-07T03:04:53.474988",
      "error": null
    },
    {
      "account": "Ollies",
      "script": "ol_pull.py",
      "exit_code": 0,
      "status": "pass",
      "timestamp": "2026-07-07T03:05:11.888820",
      "error": null
    }
  ]
}