[
  {
    "run_id": "2026-06-22T22:54:46",
    "date": "Jun 22, 2026 10:54 PM",
    "account": "Build",
    "script": "dashboard.py",
    "status": "fail",
    "error": "ValueError: Length of values (0) does not match length of index (1000) \u2014 VIP transform missing column (df.get footgun). Fixed in commit 478a497."
  },
  {
    "run_id": "2026-06-23T03:00:03",
    "date": "Jun 23, 2026 03:00 AM",
    "account": "Skyline",
    "script": "Skyline_pull.py",
    "status": "count_drop",
    "drop": 144,
    "prev_count": 4621,
    "new_count": 4477,
    "error": "Dropped 144 rows (4,621 \u2192 4,477)"
  },
  {
    "run_id": "2026-06-23T03:00:03",
    "date": "Jun 23, 2026 03:00 AM",
    "account": "Data Carz",
    "script": "dc_pull.py",
    "status": "count_drop",
    "drop": 424,
    "prev_count": 2719,
    "new_count": 2295,
    "error": "Dropped 424 rows (2,719 \u2192 2,295)"
  },
  {
    "run_id": "2026-06-23T06:00:03",
    "date": "Jun 23, 2026 06:00 AM",
    "account": "Data Carz",
    "script": "dc_pull.py",
    "status": "count_drop",
    "drop": 140,
    "prev_count": 2295,
    "new_count": 2155,
    "error": "Dropped 140 rows (2,295 \u2192 2,155)"
  },
  {
    "run_id": "2026-06-23T09:04:24",
    "date": "Jun 23, 2026 09:04 AM",
    "account": "VIP",
    "script": "vip_pull.py",
    "status": "count_drop",
    "drop": 2084,
    "prev_count": 3066,
    "new_count": 982,
    "error": "Dropped 2,084 rows (3,066 \u2192 982)"
  },
  {
    "run_id": "2026-06-23T09:04:24",
    "date": "Jun 23, 2026 09:04 AM",
    "account": "Reno Cab",
    "script": "rc_pull.py",
    "status": "count_drop",
    "drop": 1633,
    "prev_count": 2460,
    "new_count": 827,
    "error": "Dropped 1,633 rows (2,460 \u2192 827)"
  },
  {
    "run_id": "2026-06-23T09:04:24",
    "date": "Jun 23, 2026 09:04 AM",
    "account": "Circle Taxi",
    "script": "ct_pull.py",
    "status": "count_drop",
    "drop": 746,
    "prev_count": 1267,
    "new_count": 521,
    "error": "Dropped 746 rows (1,267 \u2192 521)"
  },
  {
    "run_id": "2026-06-23T09:04:24",
    "date": "Jun 23, 2026 09:04 AM",
    "account": "YCDC",
    "script": "ycdc_pull.py",
    "status": "count_drop",
    "drop": 1593,
    "prev_count": 2387,
    "new_count": 794,
    "error": "Dropped 1,593 rows (2,387 \u2192 794)"
  },
  {
    "run_id": "2026-06-23T09:04:24",
    "date": "Jun 23, 2026 09:04 AM",
    "account": "Build",
    "script": "dashboard.py",
    "status": "fail",
    "error": "    raise ValueError(\n    ...<4 lines>...\n    )\nValueError: Length of values (0) does not match length of index (827)"
  },
  {
    "run_id": "2026-06-23T11:00:02",
    "date": "Jun 23, 2026 11:00 AM",
    "account": "Britelift Chat",
    "script": "britelift_pull.py",
    "status": "fail",
    "error": "    r = self.request(\"get\", url, params=params)\n  File \"C:\\Users\\Mike Woo Cerna\\AppData\\Local\\Programs\\Python\\Python313\\Lib\\site-packages\\gspread\\http_client.py\", line 128, in request\n    raise APIError(response)\ngspread.exceptions.APIError: APIError: [503]: The service is currently unavailable."
  },
  {
    "run_id": "2026-06-23T11:00:02",
    "date": "Jun 23, 2026 11:00 AM",
    "account": "RideX",
    "script": "Ridex_pull.py",
    "status": "not_reached",
    "error": null
  },
  {
    "run_id": "2026-06-23T11:00:02",
    "date": "Jun 23, 2026 11:00 AM",
    "account": "Hamilton",
    "script": "Hamilton_pull.py",
    "status": "not_reached",
    "error": null
  },
  {
    "run_id": "2026-06-23T11:00:02",
    "date": "Jun 23, 2026 11:00 AM",
    "account": "Skyline",
    "script": "Skyline_pull.py",
    "status": "not_reached",
    "error": null
  },
  {
    "run_id": "2026-06-23T11:00:02",
    "date": "Jun 23, 2026 11:00 AM",
    "account": "VIP",
    "script": "vip_pull.py",
    "status": "not_reached",
    "error": null
  },
  {
    "run_id": "2026-06-23T11:00:02",
    "date": "Jun 23, 2026 11:00 AM",
    "account": "C&H",
    "script": "ch_pull.py",
    "status": "not_reached",
    "error": null
  },
  {
    "run_id": "2026-06-23T11:00:02",
    "date": "Jun 23, 2026 11:00 AM",
    "account": "Reno Cab",
    "script": "rc_pull.py",
    "status": "not_reached",
    "error": null
  },
  {
    "run_id": "2026-06-23T11:00:02",
    "date": "Jun 23, 2026 11:00 AM",
    "account": "Trans Iowa",
    "script": "ti_pull.py",
    "status": "not_reached",
    "error": null
  },
  {
    "run_id": "2026-06-23T11:00:02",
    "date": "Jun 23, 2026 11:00 AM",
    "account": "Data Carz",
    "script": "dc_pull.py",
    "status": "not_reached",
    "error": null
  },
  {
    "run_id": "2026-06-23T11:00:02",
    "date": "Jun 23, 2026 11:00 AM",
    "account": "Associated Cab",
    "script": "ac_pull.py",
    "status": "not_reached",
    "error": null
  },
  {
    "run_id": "2026-06-23T11:00:02",
    "date": "Jun 23, 2026 11:00 AM",
    "account": "Ollies",
    "script": "ol_pull.py",
    "status": "not_reached",
    "error": null
  },
  {
    "run_id": "2026-06-23T11:00:02",
    "date": "Jun 23, 2026 11:00 AM",
    "account": "Circle Taxi",
    "script": "ct_pull.py",
    "status": "not_reached",
    "error": null
  },
  {
    "run_id": "2026-06-23T11:00:02",
    "date": "Jun 23, 2026 11:00 AM",
    "account": "YCOV",
    "script": "ycov_pull.py",
    "status": "not_reached",
    "error": null
  },
  {
    "run_id": "2026-06-23T11:00:02",
    "date": "Jun 23, 2026 11:00 AM",
    "account": "Kelowna",
    "script": "kel_pull.py",
    "status": "not_reached",
    "error": null
  },
  {
    "run_id": "2026-06-23T11:00:02",
    "date": "Jun 23, 2026 11:00 AM",
    "account": "Vermont",
    "script": "vt_pull.py",
    "status": "not_reached",
    "error": null
  },
  {
    "run_id": "2026-06-23T11:00:02",
    "date": "Jun 23, 2026 11:00 AM",
    "account": "YCDC",
    "script": "ycdc_pull.py",
    "status": "not_reached",
    "error": null
  },
  {
    "run_id": "2026-06-23T11:00:02",
    "date": "Jun 23, 2026 11:00 AM",
    "account": "Blueline",
    "script": "bl_pull.py",
    "status": "not_reached",
    "error": null
  },
  {
    "run_id": "2026-06-23T15:00:02",
    "date": "Jun 23, 2026 03:00 PM",
    "account": "Skyline",
    "script": "Skyline_pull.py",
    "status": "count_drop",
    "drop": 7572,
    "prev_count": 14429,
    "new_count": 6857,
    "error": "Dropped 7,572 rows (14,429 \u2192 6,857)"
  },
  {
    "run_id": "2026-06-23T19:00:02",
    "date": "Jun 23, 2026 07:00 PM",
    "account": "Skyline",
    "script": "Skyline_pull.py",
    "status": "fail",
    "error": "Traceback (most recent call last):\n  File \"C:\\Users\\Mike Woo Cerna\\AppData\\Local\\Programs\\Python\\Python313\\Lib\\site-packages\\openpyxl\\worksheet\\_writer.py\", line 32, in _openpyxl_shutdown\n    os.remove(path)\nPermissionError: [WinError 32] The process cannot access the file because it is being used by another process: 'C:\\\\Users\\\\MIKEWO~1\\\\AppData\\\\Local\\\\Temp\\\\openpyxl.6271wd_q'"
  },
  {
    "run_id": "2026-06-23T19:00:02",
    "date": "Jun 23, 2026 07:00 PM",
    "account": "VIP",
    "script": "vip_pull.py",
    "status": "not_reached",
    "error": null
  },
  {
    "run_id": "2026-06-23T19:00:02",
    "date": "Jun 23, 2026 07:00 PM",
    "account": "C&H",
    "script": "ch_pull.py",
    "status": "not_reached",
    "error": null
  },
  {
    "run_id": "2026-06-23T19:00:02",
    "date": "Jun 23, 2026 07:00 PM",
    "account": "Reno Cab",
    "script": "rc_pull.py",
    "status": "not_reached",
    "error": null
  },
  {
    "run_id": "2026-06-23T19:00:02",
    "date": "Jun 23, 2026 07:00 PM",
    "account": "Trans Iowa",
    "script": "ti_pull.py",
    "status": "not_reached",
    "error": null
  },
  {
    "run_id": "2026-06-23T19:00:02",
    "date": "Jun 23, 2026 07:00 PM",
    "account": "Data Carz",
    "script": "dc_pull.py",
    "status": "not_reached",
    "error": null
  },
  {
    "run_id": "2026-06-23T19:00:02",
    "date": "Jun 23, 2026 07:00 PM",
    "account": "Associated Cab",
    "script": "ac_pull.py",
    "status": "not_reached",
    "error": null
  },
  {
    "run_id": "2026-06-23T19:00:02",
    "date": "Jun 23, 2026 07:00 PM",
    "account": "Ollies",
    "script": "ol_pull.py",
    "status": "not_reached",
    "error": null
  },
  {
    "run_id": "2026-06-23T19:00:02",
    "date": "Jun 23, 2026 07:00 PM",
    "account": "Circle Taxi",
    "script": "ct_pull.py",
    "status": "not_reached",
    "error": null
  },
  {
    "run_id": "2026-06-23T19:00:02",
    "date": "Jun 23, 2026 07:00 PM",
    "account": "YCOV",
    "script": "ycov_pull.py",
    "status": "not_reached",
    "error": null
  },
  {
    "run_id": "2026-06-23T19:00:02",
    "date": "Jun 23, 2026 07:00 PM",
    "account": "Kelowna",
    "script": "kel_pull.py",
    "status": "not_reached",
    "error": null
  },
  {
    "run_id": "2026-06-23T19:00:02",
    "date": "Jun 23, 2026 07:00 PM",
    "account": "Vermont",
    "script": "vt_pull.py",
    "status": "not_reached",
    "error": null
  },
  {
    "run_id": "2026-06-23T19:00:02",
    "date": "Jun 23, 2026 07:00 PM",
    "account": "YCDC",
    "script": "ycdc_pull.py",
    "status": "not_reached",
    "error": null
  },
  {
    "run_id": "2026-06-23T19:00:02",
    "date": "Jun 23, 2026 07:00 PM",
    "account": "Blueline",
    "script": "bl_pull.py",
    "status": "not_reached",
    "error": null
  },
  {
    "run_id": "2026-06-23T19:23:13",
    "date": "Jun 23, 2026 07:23 PM",
    "account": "Skyline",
    "script": "Skyline_pull.py",
    "status": "high_volume",
    "error": "Warning: 14,297 rows (threshold 10,000)"
  },
  {
    "run_id": "2026-06-23T20:11:41",
    "date": "Jun 23, 2026 08:11 PM",
    "account": "Reno Cab",
    "script": "rc_pull.py",
    "status": "healed",
    "action": "repull",
    "error": "Count dropped 2,487 \u2192 1,712. Re-pull recovered 2,487 rows."
  },
  {
    "run_id": "2026-06-24T03:00:02",
    "date": "Jun 24, 2026 03:00 AM",
    "account": "Skyline",
    "script": "Skyline_pull.py",
    "status": "count_drop",
    "drop": 6530,
    "prev_count": 14447,
    "new_count": 7917,
    "error": "Dropped 6,530 rows (14,447 \u2192 7,917)"
  },
  {
    "run_id": "2026-06-24T03:00:02",
    "date": "Jun 24, 2026 03:00 AM",
    "account": "Circle Taxi",
    "script": "ct_pull.py",
    "status": "count_drop",
    "drop": 23,
    "prev_count": 523,
    "new_count": 500,
    "error": "Dropped 23 rows (523 \u2192 500)"
  },
  {
    "run_id": "2026-06-24T08:45:27",
    "date": "Jun 24, 2026 08:45 AM",
    "account": "kel_pull.py",
    "script": "kel_pull.py",
    "status": "healed",
    "action": "retry",
    "error": "Failed on attempt 1, recovered automatically on retry."
  },
  {
    "run_id": "2026-06-24T11:00:02",
    "date": "Jun 24, 2026 11:00 AM",
    "account": "Circle Taxi",
    "script": "ct_pull.py",
    "status": "count_drop",
    "drop": 771,
    "prev_count": 1283,
    "new_count": 512,
    "error": "Dropped 771 rows (1,283 \u2192 512)"
  },
  {
    "run_id": "2026-06-24T11:48:07",
    "date": "Jun 24, 2026 11:48 AM",
    "account": "Ridex_pull.py",
    "script": "Ridex_pull.py",
    "status": "healed",
    "action": "retry",
    "error": "Failed on attempt 1, recovered automatically on retry."
  },
  {
    "run_id": "2026-06-25T15:00:02",
    "date": "Jun 25, 2026 03:00 PM",
    "account": "britelift_pull.py",
    "script": "britelift_pull.py",
    "status": "healed",
    "action": "retry",
    "error": "Failed on attempt 1, recovered automatically on retry."
  },
  {
    "run_id": "2026-06-26T03:00:02",
    "date": "Jun 26, 2026 03:00 AM",
    "account": "parentis_pull.py",
    "script": "parentis_pull.py",
    "status": "healed",
    "action": "retry",
    "error": "Failed on attempt 1, recovered automatically on retry."
  },
  {
    "run_id": "2026-06-26T11:00:02",
    "date": "Jun 26, 2026 11:00 AM",
    "account": "britelift_pull.py",
    "script": "britelift_pull.py",
    "status": "healed",
    "action": "retry",
    "error": "Failed on attempt 1, recovered automatically on retry."
  },
  {
    "run_id": "2026-06-26T19:00:03",
    "date": "Jun 26, 2026 07:00 PM",
    "account": "dc_pull.py",
    "script": "dc_pull.py",
    "status": "healed",
    "action": "retry",
    "error": "Failed on attempt 1, recovered automatically on retry."
  },
  {
    "run_id": "2026-06-26T22:00:03",
    "date": "Jun 26, 2026 10:00 PM",
    "account": "Kelowna",
    "script": "kel_pull.py",
    "status": "count_drop",
    "drop": 21,
    "prev_count": 2353,
    "new_count": 2332,
    "error": "Dropped 21 rows (2,353 \u2192 2,332)"
  },
  {
    "run_id": "2026-06-26T23:06:17",
    "date": "Jun 26, 2026 11:06 PM",
    "account": "Kelowna",
    "script": "C:\\Users\\Mike Woo Cerna\\Documents\\PB\\Quality\\Kelowna\\kel_pull.py",
    "status": "healed",
    "action": "appsscript_trigger",
    "error": "Count drop auto-recovered. Apps Script re-triggered, dashboard rebuilt and pushed."
  },
  {
    "run_id": "2026-06-26T23:41:44",
    "date": "Jun 26, 2026 11:41 PM",
    "account": "Kelowna",
    "script": "C:\\Users\\Mike Woo Cerna\\Documents\\PB\\Quality\\Kelowna\\kel_pull.py",
    "status": "healed",
    "action": "appsscript_trigger",
    "prev_count": 2332,
    "healed_count": 0,
    "error": "Count drop auto-recovered. Apps Script re-triggered, dashboard rebuilt and pushed. Rows before drop: 2,332 \u2192 rows after heal: unknown."
  },
  {
    "run_id": "2026-06-27T03:00:02",
    "date": "Jun 27, 2026 03:00 AM",
    "account": "parentis_pull.py",
    "script": "parentis_pull.py",
    "status": "healed",
    "action": "retry",
    "error": "Failed on attempt 1, recovered automatically on retry."
  },
  {
    "run_id": "2026-06-27T11:00:02",
    "date": "Jun 27, 2026 11:00 AM",
    "account": "ol_pull.py",
    "script": "ol_pull.py",
    "status": "healed",
    "action": "retry",
    "error": "Failed on attempt 1, recovered automatically on retry."
  },
  {
    "run_id": "2026-06-27T19:00:02",
    "date": "Jun 27, 2026 07:00 PM",
    "account": "Hamilton",
    "script": "Hamilton_pull.py",
    "status": "count_drop",
    "drop": 1032,
    "prev_count": 3423,
    "new_count": 2391,
    "error": "Dropped 1,032 rows (3,423 \u2192 2,391)"
  },
  {
    "run_id": "2026-06-27T19:00:02",
    "date": "Jun 27, 2026 07:00 PM",
    "account": "Data Carz",
    "script": "dc_pull.py",
    "status": "count_drop",
    "drop": 801,
    "prev_count": 2825,
    "new_count": 2024,
    "error": "Dropped 801 rows (2,825 \u2192 2,024)"
  },
  {
    "run_id": "2026-06-27T19:00:02",
    "date": "Jun 27, 2026 07:00 PM",
    "account": "Ollies",
    "script": "ol_pull.py",
    "status": "count_drop",
    "drop": 455,
    "prev_count": 1891,
    "new_count": 1436,
    "error": "Dropped 455 rows (1,891 \u2192 1,436)"
  },
  {
    "run_id": "2026-06-27T21:42:03",
    "date": "Jun 27, 2026 09:42 PM",
    "account": "Hamilton",
    "script": "C:\\Users\\Mike Woo Cerna\\Documents\\PB\\Quality\\Hamilton\\Hamilton_pull.py",
    "status": "healed",
    "action": "appsscript_trigger",
    "prev_count": 3423,
    "healed_count": 3423,
    "error": "Count drop auto-recovered. Apps Script re-triggered, dashboard rebuilt and pushed. Rows before drop: 3,423 \u2192 rows after heal: 3,423 (100%)."
  }
]