{
  "run_id": "2026-06-23T09:04:24",
  "started_at": "2026-06-23T09:04:24.113244",
  "finished_at": null,
  "status": "running",
  "failed_at": null,
  "steps": [
    {
      "account": "Masterlist",
      "script": "masterlist_fetch.py",
      "exit_code": 0,
      "status": "pass",
      "timestamp": "2026-06-23T09:04:37.678157",
      "error": null
    },
    {
      "account": "Coaching",
      "script": "asana_pull.py",
      "exit_code": 0,
      "status": "pass",
      "timestamp": "2026-06-23T09:04:54.050160",
      "error": null
    },
    {
      "account": "M7",
      "script": "m7_pull.py",
      "exit_code": 0,
      "status": "pass",
      "timestamp": "2026-06-23T09:05:12.738401",
      "error": null
    },
    {
      "account": "Parentis Health",
      "script": "parentis_pull.py",
      "exit_code": 0,
      "status": "pass",
      "timestamp": "2026-06-23T09:05:27.979931",
      "error": null
    },
    {
      "account": "Britelift",
      "script": "britelift_pull.py",
      "exit_code": 0,
      "status": "pass",
      "timestamp": "2026-06-23T09:05:43.385100",
      "error": null
    },
    {
      "account": "Britelift Chat",
      "script": "britelift_pull.py",
      "exit_code": 0,
      "status": "pass",
      "timestamp": "2026-06-23T09:05:58.050208",
      "error": null
    },
    {
      "account": "RideX",
      "script": "Ridex_pull.py",
      "exit_code": 0,
      "status": "pass",
      "timestamp": "2026-06-23T09:06:13.837745",
      "error": null
    },
    {
      "account": "Hamilton",
      "script": "Hamilton_pull.py",
      "exit_code": 0,
      "status": "pass",
      "timestamp": "2026-06-23T09:06:45.274689",
      "error": null
    },
    {
      "account": "Skyline",
      "script": "Skyline_pull.py",
      "exit_code": 0,
      "status": "pass",
      "timestamp": "2026-06-23T09:07:19.870897",
      "error": null
    },
    {
      "account": "VIP",
      "script": "vip_pull.py",
      "exit_code": 0,
      "status": "pass",
      "timestamp": "2026-06-23T09:07:38.714880",
      "error": null
    },
    {
      "account": "C&H",
      "script": "ch_pull.py",
      "exit_code": 0,
      "status": "pass",
      "timestamp": "2026-06-23T09:07:56.915147",
      "error": null
    },
    {
      "account": "Reno Cab",
      "script": "rc_pull.py",
      "exit_code": 0,
      "status": "pass",
      "timestamp": "2026-06-23T09:08:16.322050",
      "error": null
    },
    {
      "account": "Trans Iowa",
      "script": "ti_pull.py",
      "exit_code": 0,
      "status": "pass",
      "timestamp": "2026-06-23T09:08:32.401967",
      "error": null
    },
    {
      "account": "Data Carz",
      "script": "dc_pull.py",
      "exit_code": 0,
      "status": "pass",
      "timestamp": "2026-06-23T09:08:58.619923",
      "error": null
    },
    {
      "account": "Associated Cab",
      "script": "ac_pull.py",
      "exit_code": 0,
      "status": "pass",
      "timestamp": "2026-06-23T09:09:21.333900",
      "error": null
    },
    {
      "account": "Ollies",
      "script": "ol_pull.py",
      "exit_code": 0,
      "status": "pass",
      "timestamp": "2026-06-23T09:09:44.181383",
      "error": null
    },
    {
      "account": "Circle Taxi",
      "script": "ct_pull.py",
      "exit_code": 0,
      "status": "pass",
      "timestamp": "2026-06-23T09:10:01.304523",
      "error": null
    },
    {
      "account": "YCOV",
      "script": "ycov_pull.py",
      "exit_code": 0,
      "status": "pass",
      "timestamp": "2026-06-23T09:10:19.012868",
      "error": null
    },
    {
      "account": "Kelowna",
      "script": "kel_pull.py",
      "exit_code": 0,
      "status": "pass",
      "timestamp": "2026-06-23T09:10:42.393024",
      "error": null
    },
    {
      "account": "Vermont",
      "script": "vt_pull.py",
      "exit_code": 0,
      "status": "pass",
      "timestamp": "2026-06-23T09:10:59.658108",
      "error": null
    },
    {
      "account": "YCDC",
      "script": "ycdc_pull.py",
      "exit_code": 0,
      "status": "pass",
      "timestamp": "2026-06-23T09:11:16.438606",
      "error": null
    }
  ]
}