{
  "run_id": "2026-07-02T11:00:01",
  "started_at": "2026-07-02T11:00:01.322635",
  "finished_at": null,
  "status": "running",
  "failed_at": null,
  "steps": [
    {
      "account": "Masterlist",
      "script": "masterlist_fetch.py",
      "exit_code": 0,
      "status": "pass",
      "timestamp": "2026-07-02T11:00:14.300581",
      "error": null
    },
    {
      "account": "Coaching",
      "script": "asana_pull.py",
      "exit_code": 0,
      "status": "pass",
      "timestamp": "2026-07-02T11:00:24.393026",
      "error": null
    },
    {
      "account": "M7",
      "script": "m7_pull.py",
      "exit_code": 0,
      "status": "pass",
      "timestamp": "2026-07-02T11:00:35.514795",
      "error": null
    },
    {
      "account": "Parentis Health",
      "script": "parentis_pull.py",
      "exit_code": 0,
      "status": "pass",
      "timestamp": "2026-07-02T11:00:44.490588",
      "error": null
    },
    {
      "account": "Britelift",
      "script": "britelift_pull.py",
      "exit_code": 0,
      "status": "pass",
      "timestamp": "2026-07-02T11:00:54.165144",
      "error": null
    },
    {
      "account": "Britelift Chat",
      "script": "britelift_pull.py",
      "exit_code": 0,
      "status": "pass",
      "timestamp": "2026-07-02T11:01:03.943964",
      "error": null
    },
    {
      "account": "RideX",
      "script": "Ridex_pull.py",
      "exit_code": 0,
      "status": "pass",
      "timestamp": "2026-07-02T11:01:13.007230",
      "error": null
    },
    {
      "account": "Hamilton",
      "script": "Hamilton_pull.py",
      "exit_code": 0,
      "status": "pass",
      "timestamp": "2026-07-02T11:01:35.889257",
      "error": null
    },
    {
      "account": "Skyline",
      "script": "Skyline_pull.py",
      "exit_code": 0,
      "status": "pass",
      "timestamp": "2026-07-02T11:02:37.419111",
      "error": null
    },
    {
      "account": "VIP",
      "script": "vip_pull.py",
      "exit_code": 0,
      "status": "pass",
      "timestamp": "2026-07-02T11:03:03.478134",
      "error": null
    },
    {
      "account": "C&H",
      "script": "ch_pull.py",
      "exit_code": 0,
      "status": "pass",
      "timestamp": "2026-07-02T11:03:13.979092",
      "error": null
    },
    {
      "account": "Reno Cab",
      "script": "rc_pull.py",
      "exit_code": 0,
      "status": "pass",
      "timestamp": "2026-07-02T11:03:29.788733",
      "error": null
    },
    {
      "account": "Trans Iowa",
      "script": "ti_pull.py",
      "exit_code": 0,
      "status": "pass",
      "timestamp": "2026-07-02T11:03:40.304430",
      "error": null
    },
    {
      "account": "Data Carz",
      "script": "dc_pull.py",
      "exit_code": 0,
      "status": "pass",
      "timestamp": "2026-07-02T11:03:58.865032",
      "error": null
    },
    {
      "account": "Associated Cab",
      "script": "ac_pull.py",
      "exit_code": 0,
      "status": "pass",
      "timestamp": "2026-07-02T11:04:16.279840",
      "error": null
    },
    {
      "account": "Ollies",
      "script": "ol_pull.py",
      "exit_code": 0,
      "status": "pass",
      "timestamp": "2026-07-02T11:04:33.272418",
      "error": null
    },
    {
      "account": "Circle Taxi",
      "script": "ct_pull.py",
      "exit_code": 0,
      "status": "pass",
      "timestamp": "2026-07-02T11:04:47.873996",
      "error": null
    },
    {
      "account": "YCOV",
      "script": "ycov_pull.py",
      "exit_code": 0,
      "status": "pass",
      "timestamp": "2026-07-02T11:05:02.472970",
      "error": null
    },
    {
      "account": "Kelowna",
      "script": "kel_pull.py",
      "exit_code": 0,
      "status": "pass",
      "timestamp": "2026-07-02T11:05:20.194074",
      "error": null
    }
  ]
}